airflow_add_ons/__init__.py
airflow_add_ons/hooks/__init__.py
airflow_add_ons/hooks/gmail_imap_hooks.py
airflow_add_ons/operators/__init__.py
airflow_add_ons/operators/athena_operators.py
airflow_add_ons/operators/empty_file_to_gcs.py
airflow_add_ons/operators/glue_operators.py
airflow_add_ons/operators/lambda_operators.py
airflow_add_ons/operators/python_operators.py
airflow_add_ons/operators/slack_operators.py
airflow_add_ons/operators/zip_operators.py
airflow_add_ons/sensors/__init__.py
airflow_add_ons/sensors/gcs_sensors.py
airflow_add_ons/sensors/glue_sensors.py
airflow_add_ons/sensors/gmail_imap_sensors.py
airflow_add_ons/sensors/s3_sensors.py
airflow_add_ons-0.2.15.dist-info/METADATA
airflow_add_ons-0.2.15.dist-info/WHEEL
airflow_add_ons-0.2.15.dist-info/top_level.txt
airflow_add_ons-0.2.15.dist-info/RECORD
